hyperchain/__init__.py
hyperchain/chain/__init__.py
hyperchain/chain/chain.py
hyperchain/chain/chain_result.py
hyperchain/chain/chain_sequence.py
hyperchain/chain/function_chain.py
hyperchain/chain/function_map_chain.py
hyperchain/chain/llm_chain.py
hyperchain/llm_runners/__init__.py
hyperchain/llm_runners/error_handler.py
hyperchain/llm_runners/hf_runner.py
hyperchain/llm_runners/llm_result.py
hyperchain/llm_runners/llm_runner.py
hyperchain/llm_runners/masked_model_runner.py
hyperchain/llm_runners/openai_runner.py
hyperchain/llm_runners/t5_model_runner.py
hyperchain/llm_runners/utils.py
hyperchain/llm_runners/response_length_prediction/__init__.py
hyperchain/llm_runners/response_length_prediction/automatas.py
hyperchain/llm_runners/response_length_prediction/parts_of_speech.py
hyperchain/llm_runners/response_length_prediction/prediction.py
hyperchain/llm_runners/response_length_prediction/svr_data.py
hyperchain/llm_runners/response_length_prediction/task_extraction.py
hyperchain/llm_runners/response_length_prediction/task_parsing.py
hyperchain/llm_runners/response_length_prediction/word_tagging.py
hyperchain/prompt_templates/__init__.py
hyperchain/prompt_templates/base_template.py
hyperchain/prompt_templates/chat_template.py
hyperchain/prompt_templates/mask_to_sentinel_template.py
hyperchain/prompt_templates/string_template.py
hyperchain-0.1.3.dist-info/LICENSE
hyperchain-0.1.3.dist-info/METADATA
hyperchain-0.1.3.dist-info/WHEEL
hyperchain-0.1.3.dist-info/top_level.txt
hyperchain-0.1.3.dist-info/RECORD
