Metadata-Version: 2.1
Name: hyperchain
Version: 0.1.3
Summary: A high-performance LLM chaining framework for python
Author: Damian Ziaber
License-File: LICENSE
Requires-Dist: openai >=1.0.0
Requires-Dist: tiktoken
Requires-Dist: scipy
Requires-Dist: numpy
Requires-Dist: transformers
Provides-Extra: test
Requires-Dist: pytest ; extra == 'test'
Requires-Dist: pytest-cov ; extra == 'test'
Requires-Dist: pytest-asyncio ; extra == 'test'
